pyego/__init__.py
pyego/__main__.py
pyego/cli.py
pyego-0.1.2.dist-info/entry_points.txt
pyego-0.1.2.dist-info/WHEEL
pyego-0.1.2.dist-info/METADATA
pyego-0.1.2.dist-info/RECORD
