Metadata-Version: 2.1
Name: pyego
Version: 0.1.2
Summary: Short distribution description.
Home-page: https://github.com/johndoe/reponame/
License: MIT
Author: John Doe
Author-email: john.doe@ema.il
Maintainer: Smith Doe
Maintainer-email: smith.doe@ema.il
Requires-Python: >=3.9,<4.0
Classifier: Environment :: Console
Classifier: Intended Audience :: Developers
Classifier: License :: OSI Approved :: MIT License
Classifier: Natural Language :: English
Classifier: Operating System :: OS Independent
Classifier: Programming Language :: Python :: 3
Classifier: Programming Language :: Python :: 3.10
Classifier: Programming Language :: Python :: 3.9
Classifier: Topic :: Utilities
Provides-Extra: mysql
Provides-Extra: pgsql
Requires-Dist: requests (>=2.28.1,<3.0.0)
Requires-Dist: ujson (>=5.4.0,<6.0.0)
Project-URL: Bug Reports, https://github.com/johndoe/reponame/issues
Project-URL: Documentation, https://github.com/johndoe/reponame/
Project-URL: Repository, https://github.com/johndoe/reponame/
Project-URL: Sponsorship, https://github.com/sponsors/johndoe
